{
"type": "FeatureCollection",
"name": "sheet1",
"crs": { "type": "name", "properties": { "name": "urn:ogc:def:crs:EPSG::3857" } },
"features": [
{ "type": "Feature", "properties": { "Start Date": 43674, "End Date": 43674, "Portfolio name": "Not grouped", "Currency": "USD", "Campaign Name": "OraSwift SKU2 Auto", "Ad Group Name": "OraSwift", "Targeting": "*", "Match Type": "-", "Customer Search Term": "b000052ye1", "Impressions": 191, "Clicks": 1, "Click-Thru Rate (CTR)": 0.005235602094240838, "Cost Per Click (CPC)": 1.77, "Spend": 1.77, "7 Day Total Sales ": 0.0, "Total Return on Advertising Spend (RoAS)": 0.0, "7 Day Total Orders (#)": 0, "7 Day Total Units (#)": 0, "7 Day Conversion Rate": 0.0, "7 Day Advertised SKU Units (#)": 0, "7 Day Other SKU Units (#)": 0, "7 Day Advertised SKU Sales ": 0.0, "7 Day Other SKU Sales ": 0 }, "geometry": null },
{ "type": "Feature", "properties": { "Start Date": 43654, "End Date": 43659, "Portfolio name": "Not grouped", "Currency": "USD", "Campaign Name": "OraSwift SKU2 Auto", "Ad Group Name": "OraSwift", "Targeting": "*", "Match Type": "-", "Customer Search Term": "b000052ye9", "Impressions": 480, "Clicks": 2, "Click-Thru Rate (CTR)": 0.0041666666666666666, "Cost Per Click (CPC)": 1.87, "Spend": 3.74, "7 Day Total Sales ": 0.0, "Total Return on Advertising Spend (RoAS)": 0.0, "7 Day Total Orders (#)": 0, "7 Day Total Units (#)": 0, "7 Day Conversion Rate": 0.0, "7 Day Advertised SKU Units (#)": 0, "7 Day Other SKU Units (#)": 0, "7 Day Advertised SKU Sales ": 0.0, "7 Day Other SKU Sales ": 0 }, "geometry": null },
{ "type": "Feature", "properties": { "Start Date": 43662, "End Date": 43662, "Portfolio name": "Not grouped", "Currency": "USD", "Campaign Name": "OraSwift SKU2 Auto", "Ad Group Name": "OraSwift", "Targeting": "*", "Match Type": "-", "Customer Search Term": "b00007ikkc", "Impressions": 11, "Clicks": 1, "Click-Thru Rate (CTR)": 0.090909090909090912, "Cost Per Click (CPC)": 1.21, "Spend": 1.21, "7 Day Total Sales ": 0.0, "Total Return on Advertising Spend (RoAS)": 0.0, "7 Day Total Orders (#)": 0, "7 Day Total Units (#)": 0, "7 Day Conversion Rate": 0.0, "7 Day Advertised SKU Units (#)": 0, "7 Day Other SKU Units (#)": 0, "7 Day Advertised SKU Sales ": 0.0, "7 Day Other SKU Sales ": 0 }, "geometry": null },
{ "type": "Feature", "properties": { "Start Date": 43655, "End Date": 43655, "Portfolio name": "Not grouped", "Currency": "USD", "Campaign Name": "OraSwift SKU2 Auto", "Ad Group Name": "OraSwift", "Targeting": "*", "Match Type": "-", "Customer Search Term": "b00014e1hs", "Impressions": 2, "Clicks": 1, "Click-Thru Rate (CTR)": 0.5, "Cost Per Click (CPC)": 1.98, "Spend": 1.98, "7 Day Total Sales ": 0.0, "Total Return on Advertising Spend (RoAS)": 0.0, "7 Day Total Orders (#)": 0, "7 Day Total Units (#)": 0, "7 Day Conversion Rate": 0.0, "7 Day Advertised SKU Units (#)": 0, "7 Day Other SKU Units (#)": 0, "7 Day Advertised SKU Sales ": 0.0, "7 Day Other SKU Sales ": 0 }, "geometry": null },
{ "type": "Feature", "properties": { "Start Date": 43657, "End Date": 43657, "Portfolio name": "Not grouped", "Currency": "USD", "Campaign Name": "OraSwift SKU2 Auto", "Ad Group Name": "OraSwift", "Targeting": "*", "Match Type": "-", "Customer Search Term": "b0006gbej4", "Impressions": 243, "Clicks": 1, "Click-Thru Rate (CTR)": 0.00411522633744856, "Cost Per Click (CPC)": 1.39, "Spend": 1.39, "7 Day Total Sales ": 0.0, "Total Return on Advertising Spend (RoAS)": 0.0, "7 Day Total Orders (#)": 0, "7 Day Total Units (#)": 0, "7 Day Conversion Rate": 0.0, "7 Day Advertised SKU Units (#)": 0, "7 Day Other SKU Units (#)": 0, "7 Day Advertised SKU Sales ": 0.0, "7 Day Other SKU Sales ": 0 }, "geometry": null },
{ "type": "Feature", "properties": { "Start Date": 43651, "End Date": 43669, "Portfolio name": "Not grouped", "Currency": "USD", "Campaign Name": "OraSwift SKU2 Auto", "Ad Group Name": "OraSwift", "Targeting": "*", "Match Type": "-", "Customer Search Term": "b000gghsqc", "Impressions": 34, "Clicks": 2, "Click-Thru Rate (CTR)": 0.058823529411764698, "Cost Per Click (CPC)": 1.76, "Spend": 3.52, "7 Day Total Sales ": 0.0, "Total Return on Advertising Spend (RoAS)": 0.0, "7 Day Total Orders (#)": 0, "7 Day Total Units (#)": 0, "7 Day Conversion Rate": 0.0, "7 Day Advertised SKU Units (#)": 0, "7 Day Other SKU Units (#)": 0, "7 Day Advertised SKU Sales ": 0.0, "7 Day Other SKU Sales ": 0 }, "geometry": null },
{ "type": "Feature", "properties": { "Start Date": 43673, "End Date": 43673, "Portfolio name": "Not grouped", "Currency": "USD", "Campaign Name": "OraSwift SKU2 Auto", "Ad Group Name": "OraSwift", "Targeting": "*", "Match Type": "-", "Customer Search Term": "b000ggjdbk", "Impressions": 102, "Clicks": 1, "Click-Thru Rate (CTR)": 0.0098039215686274508, "Cost Per Click (CPC)": 1.41, "Spend": 1.41, "7 Day Total Sales ": 0.0, "Total Return on Advertising Spend (RoAS)": 0.0, "7 Day Total Orders (#)": 0, "7 Day Total Units (#)": 0, "7 Day Conversion Rate": 0.0, "7 Day Advertised SKU Units (#)": 0, "7 Day Other SKU Units (#)": 0, "7 Day Advertised SKU Sales ": 0.0, "7 Day Other SKU Sales ": 0 }, "geometry": null },
{ "type": "Feature", "properties": { "Start Date": 43663, "End Date": 43663, "Portfolio name": "Not grouped", "Currency": "USD", "Campaign Name": "OraSwift SKU2 Auto", "Ad Group Name": "OraSwift", "Targeting": "*", "Match Type": "-", "Customer Search Term": "b000hhlpnw", "Impressions": 4, "Clicks": 1, "Click-Thru Rate (CTR)": 0.25, "Cost Per Click (CPC)": 0.71, "Spend": 0.71, "7 Day Total Sales ": 0.0, "Total Return on Advertising Spend (RoAS)": 0.0, "7 Day Total Orders (#)": 0, "7 Day Total Units (#)": 0, "7 Day Conversion Rate": 0.0, "7 Day Advertised SKU Units (#)": 0, "7 Day Other SKU Units (#)": 0, "7 Day Advertised SKU Sales ": 0.0, "7 Day Other SKU Sales ": 0 }, "geometry": null },
{ "type": "Feature", "properties": { "Start Date": 43670, "End Date": 43670, "Portfolio name": "Not grouped", "Currency": "USD", "Campaign Name": "OraSwift SKU2 Auto", "Ad Group Name": "OraSwift", "Targeting": "*", "Match Type": "-", "Customer Search Term": "b000iefj8q", "Impressions": 5, "Clicks": 1, "Click-Thru Rate (CTR)": 0.2, "Cost Per Click (CPC)": 1.9, "Spend": 1.9, "7 Day Total Sales ": 0.0, "Total Return on Advertising Spend (RoAS)": 0.0, "7 Day Total Orders (#)": 0, "7 Day Total Units (#)": 0, "7 Day Conversion Rate": 0.0, "7 Day Advertised SKU Units (#)": 0, "7 Day Other SKU Units (#)": 0, "7 Day Advertised SKU Sales ": 0.0, "7 Day Other SKU Sales ": 0 }, "geometry": null },
{ "type": "Feature", "properties": { "Start Date": 43656, "End Date": 43657, "Portfolio name": "Not grouped", "Currency": "USD", "Campaign Name": "OraSwift SKU2 Auto", "Ad Group Name": "OraSwift", "Targeting": "*", "Match Type": "-", "Customer Search Term": "b000ku5334", "Impressions": 79, "Clicks": 2, "Click-Thru Rate (CTR)": 0.025316455696202535, "Cost Per Click (CPC)": 1.805, "Spend": 3.61, "7 Day Total Sales ": 0.0, "Total Return on Advertising Spend (RoAS)": 0.0, "7 Day Total Orders (#)": 0, "7 Day Total Units (#)": 0, "7 Day Conversion Rate": 0.0, "7 Day Advertised SKU Units (#)": 0, "7 Day Other SKU Units (#)": 0, "7 Day Advertised SKU Sales ": 0.0, "7 Day Other SKU Sales ": 0 }, "geometry": null },
{ "type": "Feature", "properties": { "Start Date": 43669, "End Date": 43676, "Portfolio name": "Not grouped", "Currency": "USD", "Campaign Name": "OraSwift SKU2 Auto", "Ad Group Name": "OraSwift", "Targeting": "*", "Match Type": "-", "Customer Search Term": "b000q4cgso", "Impressions": 9, "Clicks": 2, "Click-Thru Rate (CTR)": 0.22222222222222221, "Cost Per Click (CPC)": 1.975, "Spend": 3.95, "7 Day Total Sales ": 0.0, "Total Return on Advertising Spend (RoAS)": 0.0, "7 Day Total Orders (#)": 0, "7 Day Total Units (#)": 0, "7 Day Conversion Rate": 0.0, "7 Day Advertised SKU Units (#)": 0, "7 Day Other SKU Units (#)": 0, "7 Day Advertised SKU Sales ": 0.0, "7 Day Other SKU Sales ": 0 }, "geometry": null },
{ "type": "Feature", "properties": { "Start Date": 43664, "End Date": 43664, "Portfolio name": "Not grouped", "Currency": "USD", "Campaign Name": "OraSwift SKU2 Auto", "Ad Group Name": "OraSwift", "Targeting": "*", "Match Type": "-", "Customer Search Term": "b000qtg3me", "Impressions": 50, "Clicks": 1, "Click-Thru Rate (CTR)": 0.02, "Cost Per Click (CPC)": 2.0, "Spend": 2.0, "7 Day Total Sales ": 0.0, "Total Return on Advertising Spend (RoAS)": 0.0, "7 Day Total Orders (#)": 0, "7 Day Total Units (#)": 0, "7 Day Conversion Rate": 0.0, "7 Day Advertised SKU Units (#)": 0, "7 Day Other SKU Units (#)": 0, "7 Day Advertised SKU Sales ": 0.0, "7 Day Other SKU Sales ": 0 }, "geometry": null },
{ "type": "Feature", "properties": { "Start Date": 43651, "End Date": 43657, "Portfolio name": "Not grouped", "Currency": "USD", "Campaign Name": "OraSwift SKU2 Auto", "Ad Group Name": "OraSwift", "Targeting": "*", "Match Type": "-", "Customer Search Term": "b000y1fy10", "Impressions": 571, "Clicks": 3, "Click-Thru Rate (CTR)": 0.0052539404553415062, "Cost Per Click (CPC)": 1.64, "Spend": 4.92, "7 Day Total Sales ": 0.0, "Total Return on Advertising Spend (RoAS)": 0.0, "7 Day Total Orders (#)": 0, "7 Day Total Units (#)": 0, "7 Day Conversion Rate": 0.0, "7 Day Advertised SKU Units (#)": 0, "7 Day Other SKU Units (#)": 0, "7 Day Advertised SKU Sales ": 0.0, "7 Day Other SKU Sales ": 0 }, "geometry": null },
{ "type": "Feature", "properties": { "Start Date": 43650, "End Date": 43650, "Portfolio name": "Not grouped", "Currency": "USD", "Campaign Name": "OraSwift SKU2 Auto", "Ad Group Name": "OraSwift", "Targeting": "*", "Match Type": "-", "Customer Search Term": "b0013kdzhg", "Impressions": 6, "Clicks": 1, "Click-Thru Rate (CTR)": 0.16666666666666663, "Cost Per Click (CPC)": 1.88, "Spend": 1.88, "7 Day Total Sales ": 0.0, "Total Return on Advertising Spend (RoAS)": 0.0, "7 Day Total Orders (#)": 0, "7 Day Total Units (#)": 0, "7 Day Conversion Rate": 0.0, "7 Day Advertised SKU Units (#)": 0, "7 Day Other SKU Units (#)": 0, "7 Day Advertised SKU Sales ": 0.0, "7 Day Other SKU Sales ": 0 }, "geometry": null },
{ "type": "Feature", "properties": { "Start Date": 43648, "End Date": 43648, "Portfolio name": "Not grouped", "Currency": "USD", "Campaign Name": "OraSwift SKU2 Auto", "Ad Group Name": "OraSwift", "Targeting": "*", "Match Type": "-", "Customer Search Term": "b001fb5i9g", "Impressions": 6, "Clicks": 1, "Click-Thru Rate (CTR)": 0.16666666666666663, "Cost Per Click (CPC)": 1.93, "Spend": 1.93, "7 Day Total Sales ": 0.0, "Total Return on Advertising Spend (RoAS)": 0.0, "7 Day Total Orders (#)": 0, "7 Day Total Units (#)": 0, "7 Day Conversion Rate": 0.0, "7 Day Advertised SKU Units (#)": 0, "7 Day Other SKU Units (#)": 0, "7 Day Advertised SKU Sales ": 0.0, "7 Day Other SKU Sales ": 0 }, "geometry": null },
{ "type": "Feature", "properties": { "Start Date": 43653, "End Date": 43654, "Portfolio name": "Not grouped", "Currency": "USD", "Campaign Name": "OraSwift SKU2 Auto", "Ad Group Name": "OraSwift", "Targeting": "*", "Match Type": "-", "Customer Search Term": "b001g7ra2m", "Impressions": 70, "Clicks": 2, "Click-Thru Rate (CTR)": 0.028571428571428571, "Cost Per Click (CPC)": 1.53, "Spend": 3.06, "7 Day Total Sales ": 0.0, "Total Return on Advertising Spend (RoAS)": 0.0, "7 Day Total Orders (#)": 0, "7 Day Total Units (#)": 0, "7 Day Conversion Rate": 0.0, "7 Day Advertised SKU Units (#)": 0, "7 Day Other SKU Units (#)": 0, "7 Day Advertised SKU Sales ": 0.0, "7 Day Other SKU Sales ": 0 }, "geometry": null },
{ "type": "Feature", "properties": { "Start Date": 43658, "End Date": 43658, "Portfolio name": "Not grouped", "Currency": "USD", "Campaign Name": "OraSwift SKU2 Auto", "Ad Group Name": "OraSwift", "Targeting": "*", "Match Type": "-", "Customer Search Term": "b001gcu0re", "Impressions": 114, "Clicks": 1, "Click-Thru Rate (CTR)": 0.008771929824561403, "Cost Per Click (CPC)": 1.23, "Spend": 1.23, "7 Day Total Sales ": 0.0, "Total Return on Advertising Spend (RoAS)": 0.0, "7 Day Total Orders (#)": 0, "7 Day Total Units (#)": 0, "7 Day Conversion Rate": 0.0, "7 Day Advertised SKU Units (#)": 0, "7 Day Other SKU Units (#)": 0, "7 Day Advertised SKU Sales ": 0.0, "7 Day Other SKU Sales ": 0 }, "geometry": null },
{ "type": "Feature", "properties": { "Start Date": 43671, "End Date": 43671, "Portfolio name": "Not grouped", "Currency": "USD", "Campaign Name": "OraSwift SKU2 Auto", "Ad Group Name": "OraSwift", "Targeting": "*", "Match Type": "-", "Customer Search Term": "b001kyntlm", "Impressions": 12, "Clicks": 1, "Click-Thru Rate (CTR)": 0.083333333333333315, "Cost Per Click (CPC)": 1.78, "Spend": 1.78, "7 Day Total Sales ": 0.0, "Total Return on Advertising Spend (RoAS)": 0.0, "7 Day Total Orders (#)": 0, "7 Day Total Units (#)": 0, "7 Day Conversion Rate": 0.0, "7 Day Advertised SKU Units (#)": 0, "7 Day Other SKU Units (#)": 0, "7 Day Advertised SKU Sales ": 0.0, "7 Day Other SKU Sales ": 0 }, "geometry": null },
{ "type": "Feature", "properties": { "Start Date": 43654, "End Date": 43654, "Portfolio name": "Not grouped", "Currency": "USD", "Campaign Name": "OraSwift SKU2 Auto", "Ad Group Name": "OraSwift", "Targeting": "*", "Match Type": "-", "Customer Search Term": "b003allhlm", "Impressions": 8, "Clicks": 1, "Click-Thru Rate (CTR)": 0.125, "Cost Per Click (CPC)": 2.0, "Spend": 2.0, "7 Day Total Sales ": 0.0, "Total Return on Advertising Spend (RoAS)": 0.0, "7 Day Total Orders (#)": 0, "7 Day Total Units (#)": 0, "7 Day Conversion Rate": 0.0, "7 Day Advertised SKU Units (#)": 0, "7 Day Other SKU Units (#)": 0, "7 Day Advertised SKU Sales ": 0.0, "7 Day Other SKU Sales ": 0 }, "geometry": null },
{ "type": "Feature", "properties": { "Start Date": 43665, "End Date": 43673, "Portfolio name": "Not grouped", "Currency": "USD", "Campaign Name": "OraSwift SKU2 Auto", "Ad Group Name": "OraSwift", "Targeting": "*", "Match Type": "-", "Customer Search Term": "b003as74jo", "Impressions": 553, "Clicks": 2, "Click-Thru Rate (CTR)": 0.003616636528028933, "Cost Per Click (CPC)": 1.885, "Spend": 3.77, "7 Day Total Sales ": 0.0, "Total Return on Advertising Spend (RoAS)": 0.0, "7 Day Total Orders (#)": 0, "7 Day Total Units (#)": 0, "7 Day Conversion Rate": 0.0, "7 Day Advertised SKU Units (#)": 0, "7 Day Other SKU Units (#)": 0, "7 Day Advertised SKU Sales ": 0.0, "7 Day Other SKU Sales ": 0 }, "geometry": null },
{ "type": "Feature", "properties": { "Start Date": 43648, "End Date": 43648, "Portfolio name": "Not grouped", "Currency": "USD", "Campaign Name": "OraSwift SKU2 Auto", "Ad Group Name": "OraSwift", "Targeting": "*", "Match Type": "-", "Customer Search Term": "b003asb8fk", "Impressions": 8, "Clicks": 1, "Click-Thru Rate (CTR)": 0.125, "Cost Per Click (CPC)": 1.71, "Spend": 1.71, "7 Day Total Sales ": 0.0, "Total Return on Advertising Spend (RoAS)": 0.0, "7 Day Total Orders (#)": 0, "7 Day Total Units (#)": 0, "7 Day Conversion Rate": 0.0, "7 Day Advertised SKU Units (#)": 0, "7 Day Other SKU Units (#)": 0, "7 Day Advertised SKU Sales ": 0.0, "7 Day Other SKU Sales ": 0 }, "geometry": null },
{ "type": "Feature", "properties": { "Start Date": 43662, "End Date": 43664, "Portfolio name": "Not grouped", "Currency": "USD", "Campaign Name": "OraSwift SKU2 Auto", "Ad Group Name": "OraSwift", "Targeting": "*", "Match Type": "-", "Customer Search Term": "b003gd0i5a", "Impressions": 300, "Clicks": 2, "Click-Thru Rate (CTR)": 0.0066666666666666671, "Cost Per Click (CPC)": 1.965, "Spend": 3.93, "7 Day Total Sales ": 0.0, "Total Return on Advertising Spend (RoAS)": 0.0, "7 Day Total Orders (#)": 0, "7 Day Total Units (#)": 0, "7 Day Conversion Rate": 0.0, "7 Day Advertised SKU Units (#)": 0, "7 Day Other SKU Units (#)": 0, "7 Day Advertised SKU Sales ": 0.0, "7 Day Other SKU Sales ": 0 }, "geometry": null },
{ "type": "Feature", "properties": { "Start Date": 43665, "End Date": 43665, "Portfolio name": "Not grouped", "Currency": "USD", "Campaign Name": "OraSwift SKU2 Auto", "Ad Group Name": "OraSwift", "Targeting": "*", "Match Type": "-", "Customer Search Term": "b003hup4tm", "Impressions": 77, "Clicks": 1, "Click-Thru Rate (CTR)": 0.012987012987012986, "Cost Per Click (CPC)": 1.97, "Spend": 1.97, "7 Day Total Sales ": 0.0, "Total Return on Advertising Spend (RoAS)": 0.0, "7 Day Total Orders (#)": 0, "7 Day Total Units (#)": 0, "7 Day Conversion Rate": 0.0, "7 Day Advertised SKU Units (#)": 0, "7 Day Other SKU Units (#)": 0, "7 Day Advertised SKU Sales ": 0.0, "7 Day Other SKU Sales ": 0 }, "geometry": null },
{ "type": "Feature", "properties": { "Start Date": 43676, "End Date": 43676, "Portfolio name": "Not grouped", "Currency": "USD", "Campaign Name": "OraSwift SKU2 Auto", "Ad Group Name": "OraSwift", "Targeting": "*", "Match Type": "-", "Customer Search Term": "b004kvcv6g", "Impressions": 27, "Clicks": 1, "Click-Thru Rate (CTR)": 0.037037037037037035, "Cost Per Click (CPC)": 1.24, "Spend": 1.24, "7 Day Total Sales ": 0.0, "Total Return on Advertising Spend (RoAS)": 0.0, "7 Day Total Orders (#)": 0, "7 Day Total Units (#)": 0, "7 Day Conversion Rate": 0.0, "7 Day Advertised SKU Units (#)": 0, "7 Day Other SKU Units (#)": 0, "7 Day Advertised SKU Sales ": 0.0, "7 Day Other SKU Sales ": 0 }, "geometry": null },
{ "type": "Feature", "properties": { "Start Date": 43675, "End Date": 43675, "Portfolio name": "Not grouped", "Currency": "USD", "Campaign Name": "OraSwift SKU2 Auto", "Ad Group Name": "OraSwift", "Targeting": "*", "Match Type": "-", "Customer Search Term": "b005luss3k", "Impressions": 9, "Clicks": 1, "Click-Thru Rate (CTR)": 0.1111111111111111, "Cost Per Click (CPC)": 1.84, "Spend": 1.84, "7 Day Total Sales ": 0.0, "Total Return on Advertising Spend (RoAS)": 0.0, "7 Day Total Orders (#)": 0, "7 Day Total Units (#)": 0, "7 Day Conversion Rate": 0.0, "7 Day Advertised SKU Units (#)": 0, "7 Day Other SKU Units (#)": 0, "7 Day Advertised SKU Sales ": 0.0, "7 Day Other SKU Sales ": 0 }, "geometry": null },
{ "type": "Feature", "properties": { "Start Date": 43661, "End Date": 43668, "Portfolio name": "Not grouped", "Currency": "USD", "Campaign Name": "OraSwift SKU2 Auto", "Ad Group Name": "OraSwift", "Targeting": "*", "Match Type": "-", "Customer Search Term": "b005qnqclc", "Impressions": 53, "Clicks": 2, "Click-Thru Rate (CTR)": 0.037735849056603772, "Cost Per Click (CPC)": 1.42, "Spend": 2.84, "7 Day Total Sales ": 0.0, "Total Return on Advertising Spend (RoAS)": 0.0, "7 Day Total Orders (#)": 0, "7 Day Total Units (#)": 0, "7 Day Conversion Rate": 0.0, "7 Day Advertised SKU Units (#)": 0, "7 Day Other SKU Units (#)": 0, "7 Day Advertised SKU Sales ": 0.0, "7 Day Other SKU Sales ": 0 }, "geometry": null },
{ "type": "Feature", "properties": { "Start Date": 43663, "End Date": 43672, "Portfolio name": "Not grouped", "Currency": "USD", "Campaign Name": "OraSwift SKU2 Auto", "Ad Group Name": "OraSwift", "Targeting": "*", "Match Type": "-", "Customer Search Term": "b0063i312c", "Impressions": 241, "Clicks": 2, "Click-Thru Rate (CTR)": 0.0082987551867219917, "Cost Per Click (CPC)": 1.885, "Spend": 3.77, "7 Day Total Sales ": 0.0, "Total Return on Advertising Spend (RoAS)": 0.0, "7 Day Total Orders (#)": 0, "7 Day Total Units (#)": 0, "7 Day Conversion Rate": 0.0, "7 Day Advertised SKU Units (#)": 0, "7 Day Other SKU Units (#)": 0, "7 Day Advertised SKU Sales ": 0.0, "7 Day Other SKU Sales ": 0 }, "geometry": null },
{ "type": "Feature", "properties": { "Start Date": 43649, "End Date": 43649, "Portfolio name": "Not grouped", "Currency": "USD", "Campaign Name": "OraSwift SKU2 Auto", "Ad Group Name": "OraSwift", "Targeting": "*", "Match Type": "-", "Customer Search Term": "b0083ut5j6", "Impressions": 2, "Clicks": 1, "Click-Thru Rate (CTR)": 0.5, "Cost Per Click (CPC)": 1.7, "Spend": 1.7, "7 Day Total Sales ": 0.0, "Total Return on Advertising Spend (RoAS)": 0.0, "7 Day Total Orders (#)": 0, "7 Day Total Units (#)": 0, "7 Day Conversion Rate": 0.0, "7 Day Advertised SKU Units (#)": 0, "7 Day Other SKU Units (#)": 0, "7 Day Advertised SKU Sales ": 0.0, "7 Day Other SKU Sales ": 0 }, "geometry": null },
{ "type": "Feature", "properties": { "Start Date": 43657, "End Date": 43657, "Portfolio name": "Not grouped", "Currency": "USD", "Campaign Name": "OraSwift SKU2 Auto", "Ad Group Name": "OraSwift", "Targeting": "*", "Match Type": "-", "Customer Search Term": "b0088w2tew", "Impressions": 13, "Clicks": 1, "Click-Thru Rate (CTR)": 0.076923076923076927, "Cost Per Click (CPC)": 1.69, "Spend": 1.69, "7 Day Total Sales ": 0.0, "Total Return on Advertising Spend (RoAS)": 0.0, "7 Day Total Orders (#)": 0, "7 Day Total Units (#)": 0, "7 Day Conversion Rate": 0.0, "7 Day Advertised SKU Units (#)": 0, "7 Day Other SKU Units (#)": 0, "7 Day Advertised SKU Sales ": 0.0, "7 Day Other SKU Sales ": 0 }, "geometry": null },
{ "type": "Feature", "properties": { "Start Date": 43653, "End Date": 43653, "Portfolio name": "Not grouped", "Currency": "USD", "Campaign Name": "OraSwift SKU2 Auto", "Ad Group Name": "OraSwift", "Targeting": "*", "Match Type": "-", "Customer Search Term": "b00bd490h6", "Impressions": 8, "Clicks": 1, "Click-Thru Rate (CTR)": 0.125, "Cost Per Click (CPC)": 1.08, "Spend": 1.08, "7 Day Total Sales ": 0.0, "Total Return on Advertising Spend (RoAS)": 0.0, "7 Day Total Orders (#)": 0, "7 Day Total Units (#)": 0, "7 Day Conversion Rate": 0.0, "7 Day Advertised SKU Units (#)": 0, "7 Day Other SKU Units (#)": 0, "7 Day Advertised SKU Sales ": 0.0, "7 Day Other SKU Sales ": 0 }, "geometry": null },
{ "type": "Feature", "properties": { "Start Date": 43669, "End Date": 43672, "Portfolio name": "Not grouped", "Currency": "USD", "Campaign Name": "OraSwift SKU2 Auto", "Ad Group Name": "OraSwift", "Targeting": "*", "Match Type": "-", "Customer Search Term": "b00e5pwx7e", "Impressions": 379, "Clicks": 3, "Click-Thru Rate (CTR)": 0.0079155672823219003, "Cost Per Click (CPC)": 1.87, "Spend": 5.61, "7 Day Total Sales ": 0.0, "Total Return on Advertising Spend (RoAS)": 0.0, "7 Day Total Orders (#)": 0, "7 Day Total Units (#)": 0, "7 Day Conversion Rate": 0.0, "7 Day Advertised SKU Units (#)": 0, "7 Day Other SKU Units (#)": 0, "7 Day Advertised SKU Sales ": 0.0, "7 Day Other SKU Sales ": 0 }, "geometry": null },
{ "type": "Feature", "properties": { "Start Date": 43663, "End Date": 43676, "Portfolio name": "Not grouped", "Currency": "USD", "Campaign Name": "OraSwift SKU2 Auto", "Ad Group Name": "OraSwift", "Targeting": "*", "Match Type": "-", "Customer Search Term": "b00fprcas8", "Impressions": 744, "Clicks": 2, "Click-Thru Rate (CTR)": 0.0026881720430107529, "Cost Per Click (CPC)": 0.95, "Spend": 1.9, "7 Day Total Sales ": 0.0, "Total Return on Advertising Spend (RoAS)": 0.0, "7 Day Total Orders (#)": 0, "7 Day Total Units (#)": 0, "7 Day Conversion Rate": 0.0, "7 Day Advertised SKU Units (#)": 0, "7 Day Other SKU Units (#)": 0, "7 Day Advertised SKU Sales ": 0.0, "7 Day Other SKU Sales ": 0 }, "geometry": null },
{ "type": "Feature", "properties": { "Start Date": 43654, "End Date": 43674, "Portfolio name": "Not grouped", "Currency": "USD", "Campaign Name": "OraSwift SKU2 Auto", "Ad Group Name": "OraSwift", "Targeting": "*", "Match Type": "-", "Customer Search Term": "b00gkhffkm", "Impressions": 194, "Clicks": 2, "Click-Thru Rate (CTR)": 0.010309278350515462, "Cost Per Click (CPC)": 1.955, "Spend": 3.91, "7 Day Total Sales ": 0.0, "Total Return on Advertising Spend (RoAS)": 0.0, "7 Day Total Orders (#)": 0, "7 Day Total Units (#)": 0, "7 Day Conversion Rate": 0.0, "7 Day Advertised SKU Units (#)": 0, "7 Day Other SKU Units (#)": 0, "7 Day Advertised SKU Sales ": 0.0, "7 Day Other SKU Sales ": 0 }, "geometry": null },
{ "type": "Feature", "properties": { "Start Date": 43673, "End Date": 43673, "Portfolio name": "Not grouped", "Currency": "USD", "Campaign Name": "OraSwift SKU2 Auto", "Ad Group Name": "OraSwift", "Targeting": "*", "Match Type": "-", "Customer Search Term": "b00ha71taq", "Impressions": 2, "Clicks": 1, "Click-Thru Rate (CTR)": 0.5, "Cost Per Click (CPC)": 1.8, "Spend": 1.8, "7 Day Total Sales ": 0.0, "Total Return on Advertising Spend (RoAS)": 0.0, "7 Day Total Orders (#)": 0, "7 Day Total Units (#)": 0, "7 Day Conversion Rate": 0.0, "7 Day Advertised SKU Units (#)": 0, "7 Day Other SKU Units (#)": 0, "7 Day Advertised SKU Sales ": 0.0, "7 Day Other SKU Sales ": 0 }, "geometry": null },
{ "type": "Feature", "properties": { "Start Date": 43663, "End Date": 43663, "Portfolio name": "Not grouped", "Currency": "USD", "Campaign Name": "OraSwift SKU2 Auto", "Ad Group Name": "OraSwift", "Targeting": "*", "Match Type": "-", "Customer Search Term": "b00i5movqo", "Impressions": 7, "Clicks": 1, "Click-Thru Rate (CTR)": 0.14285714285714285, "Cost Per Click (CPC)": 1.83, "Spend": 1.83, "7 Day Total Sales ": 0.0, "Total Return on Advertising Spend (RoAS)": 0.0, "7 Day Total Orders (#)": 0, "7 Day Total Units (#)": 0, "7 Day Conversion Rate": 0.0, "7 Day Advertised SKU Units (#)": 0, "7 Day Other SKU Units (#)": 0, "7 Day Advertised SKU Sales ": 0.0, "7 Day Other SKU Sales ": 0 }, "geometry": null },
{ "type": "Feature", "properties": { "Start Date": 43658, "End Date": 43664, "Portfolio name": "Not grouped", "Currency": "USD", "Campaign Name": "OraSwift SKU2 Auto", "Ad Group Name": "OraSwift", "Targeting": "*", "Match Type": "-", "Customer Search Term": "b00jad7yd4", "Impressions": 344, "Clicks": 2, "Click-Thru Rate (CTR)": 0.0058139534883720929, "Cost Per Click (CPC)": 1.445, "Spend": 2.89, "7 Day Total Sales ": 0.0, "Total Return on Advertising Spend (RoAS)": 0.0, "7 Day Total Orders (#)": 0, "7 Day Total Units (#)": 0, "7 Day Conversion Rate": 0.0, "7 Day Advertised SKU Units (#)": 0, "7 Day Other SKU Units (#)": 0, "7 Day Advertised SKU Sales ": 0.0, "7 Day Other SKU Sales ": 0 }, "geometry": null },
{ "type": "Feature", "properties": { "Start Date": 43674, "End Date": 43674, "Portfolio name": "Not grouped", "Currency": "USD", "Campaign Name": "OraSwift SKU2 Auto", "Ad Group Name": "OraSwift", "Targeting": "*", "Match Type": "-", "Customer Search Term": "b00kr0jadq", "Impressions": 3, "Clicks": 1, "Click-Thru Rate (CTR)": 0.33333333333333326, "Cost Per Click (CPC)": 1.77, "Spend": 1.77, "7 Day Total Sales ": 0.0, "Total Return on Advertising Spend (RoAS)": 0.0, "7 Day Total Orders (#)": 0, "7 Day Total Units (#)": 0, "7 Day Conversion Rate": 0.0, "7 Day Advertised SKU Units (#)": 0, "7 Day Other SKU Units (#)": 0, "7 Day Advertised SKU Sales ": 0.0, "7 Day Other SKU Sales ": 0 }, "geometry": null },
{ "type": "Feature", "properties": { "Start Date": 43656, "End Date": 43674, "Portfolio name": "Not grouped", "Currency": "USD", "Campaign Name": "OraSwift SKU2 Auto", "Ad Group Name": "OraSwift", "Targeting": "*", "Match Type": "-", "Customer Search Term": "b00nvr83mg", "Impressions": 472, "Clicks": 6, "Click-Thru Rate (CTR)": 0.012711864406779662, "Cost Per Click (CPC)": 1.62, "Spend": 9.72, "7 Day Total Sales ": 0.0, "Total Return on Advertising Spend (RoAS)": 0.0, "7 Day Total Orders (#)": 0, "7 Day Total Units (#)": 0, "7 Day Conversion Rate": 0.0, "7 Day Advertised SKU Units (#)": 0, "7 Day Other SKU Units (#)": 0, "7 Day Advertised SKU Sales ": 0.0, "7 Day Other SKU Sales ": 0 }, "geometry": null },
{ "type": "Feature", "properties": { "Start Date": 43677, "End Date": 43677, "Portfolio name": "Not grouped", "Currency": "USD", "Campaign Name": "OraSwift SKU2 Auto", "Ad Group Name": "OraSwift", "Targeting": "*", "Match Type": "-", "Customer Search Term": "b00tkkb8h0", "Impressions": 35, "Clicks": 1, "Click-Thru Rate (CTR)": 0.028571428571428571, "Cost Per Click (CPC)": 1.88, "Spend": 1.88, "7 Day Total Sales ": 0.0, "Total Return on Advertising Spend (RoAS)": 0.0, "7 Day Total Orders (#)": 0, "7 Day Total Units (#)": 0, "7 Day Conversion Rate": 0.0, "7 Day Advertised SKU Units (#)": 0, "7 Day Other SKU Units (#)": 0, "7 Day Advertised SKU Sales ": 0.0, "7 Day Other SKU Sales ": 0 }, "geometry": null },
{ "type": "Feature", "properties": { "Start Date": 43652, "End Date": 43661, "Portfolio name": "Not grouped", "Currency": "USD", "Campaign Name": "OraSwift SKU2 Auto", "Ad Group Name": "OraSwift", "Targeting": "*", "Match Type": "-", "Customer Search Term": "b00wosekp2", "Impressions": 1099, "Clicks": 3, "Click-Thru Rate (CTR)": 0.0027297543221110106, "Cost Per Click (CPC)": 1.8, "Spend": 5.4, "7 Day Total Sales ": 0.0, "Total Return on Advertising Spend (RoAS)": 0.0, "7 Day Total Orders (#)": 0, "7 Day Total Units (#)": 0, "7 Day Conversion Rate": 0.0, "7 Day Advertised SKU Units (#)": 0, "7 Day Other SKU Units (#)": 0, "7 Day Advertised SKU Sales ": 0.0, "7 Day Other SKU Sales ": 0 }, "geometry": null },
{ "type": "Feature", "properties": { "Start Date": 43648, "End Date": 43648, "Portfolio name": "Not grouped", "Currency": "USD", "Campaign Name": "OraSwift SKU2 Auto", "Ad Group Name": "OraSwift", "Targeting": "*", "Match Type": "-", "Customer Search Term": "b00yhvnlq8", "Impressions": 130, "Clicks": 1, "Click-Thru Rate (CTR)": 0.0076923076923076927, "Cost Per Click (CPC)": 1.97, "Spend": 1.97, "7 Day Total Sales ": 0.0, "Total Return on Advertising Spend (RoAS)": 0.0, "7 Day Total Orders (#)": 0, "7 Day Total Units (#)": 0, "7 Day Conversion Rate": 0.0, "7 Day Advertised SKU Units (#)": 0, "7 Day Other SKU Units (#)": 0, "7 Day Advertised SKU Sales ": 0.0, "7 Day Other SKU Sales ": 0 }, "geometry": null },
{ "type": "Feature", "properties": { "Start Date": 43655, "End Date": 43675, "Portfolio name": "Not grouped", "Currency": "USD", "Campaign Name": "OraSwift SKU2 Auto", "Ad Group Name": "OraSwift", "Targeting": "*", "Match Type": "-", "Customer Search Term": "b010wc9a38", "Impressions": 540, "Clicks": 2, "Click-Thru Rate (CTR)": 0.0037037037037037038, "Cost Per Click (CPC)": 1.98, "Spend": 3.96, "7 Day Total Sales ": 0.0, "Total Return on Advertising Spend (RoAS)": 0.0, "7 Day Total Orders (#)": 0, "7 Day Total Units (#)": 0, "7 Day Conversion Rate": 0.0, "7 Day Advertised SKU Units (#)": 0, "7 Day Other SKU Units (#)": 0, "7 Day Advertised SKU Sales ": 0.0, "7 Day Other SKU Sales ": 0 }, "geometry": null },
{ "type": "Feature", "properties": { "Start Date": 43656, "End Date": 43672, "Portfolio name": "Not grouped", "Currency": "USD", "Campaign Name": "OraSwift SKU2 Auto", "Ad Group Name": "OraSwift", "Targeting": "*", "Match Type": "-", "Customer Search Term": "b010wcgx60", "Impressions": 394, "Clicks": 4, "Click-Thru Rate (CTR)": 0.01015228426395939, "Cost Per Click (CPC)": 1.6875, "Spend": 6.75, "7 Day Total Sales ": 0.0, "Total Return on Advertising Spend (RoAS)": 0.0, "7 Day Total Orders (#)": 0, "7 Day Total Units (#)": 0, "7 Day Conversion Rate": 0.0, "7 Day Advertised SKU Units (#)": 0, "7 Day Other SKU Units (#)": 0, "7 Day Advertised SKU Sales ": 0.0, "7 Day Other SKU Sales ": 0 }, "geometry": null },
{ "type": "Feature", "properties": { "Start Date": 43652, "End Date": 43677, "Portfolio name": "Not grouped", "Currency": "USD", "Campaign Name": "OraSwift SKU2 Auto", "Ad Group Name": "OraSwift", "Targeting": "*", "Match Type": "-", "Customer Search Term": "b017gqyyxo", "Impressions": 6557, "Clicks": 21, "Click-Thru Rate (CTR)": 0.0032026841543388745, "Cost Per Click (CPC)": 1.7242857142857144, "Spend": 36.21, "7 Day Total Sales ": 19.95, "Total Advertising Cost of Sales (ACoS) ": "1.8150375939849623", "Total Return on Advertising Spend (RoAS)": 0.55095277547638766, "7 Day Total Orders (#)": 1, "7 Day Total Units (#)": 1, "7 Day Conversion Rate": 0.047619047619047616, "7 Day Advertised SKU Units (#)": 1, "7 Day Other SKU Units (#)": 0, "7 Day Advertised SKU Sales ": 19.95, "7 Day Other SKU Sales ": 0 }, "geometry": null },
{ "type": "Feature", "properties": { "Start Date": 43665, "End Date": 43675, "Portfolio name": "Not grouped", "Currency": "USD", "Campaign Name": "OraSwift SKU2 Auto", "Ad Group Name": "OraSwift", "Targeting": "*", "Match Type": "-", "Customer Search Term": "b019wvx7ru", "Impressions": 126, "Clicks": 2, "Click-Thru Rate (CTR)": 0.015873015873015872, "Cost Per Click (CPC)": 1.545, "Spend": 3.09, "7 Day Total Sales ": 0.0, "Total Return on Advertising Spend (RoAS)": 0.0, "7 Day Total Orders (#)": 0, "7 Day Total Units (#)": 0, "7 Day Conversion Rate": 0.0, "7 Day Advertised SKU Units (#)": 0, "7 Day Other SKU Units (#)": 0, "7 Day Advertised SKU Sales ": 0.0, "7 Day Other SKU Sales ": 0 }, "geometry": null },
{ "type": "Feature", "properties": { "Start Date": 43657, "End Date": 43668, "Portfolio name": "Not grouped", "Currency": "USD", "Campaign Name": "OraSwift SKU2 Auto", "Ad Group Name": "OraSwift", "Targeting": "*", "Match Type": "-", "Customer Search Term": "b019wwgpeq", "Impressions": 71, "Clicks": 2, "Click-Thru Rate (CTR)": 0.028169014084507046, "Cost Per Click (CPC)": 1.755, "Spend": 3.51, "7 Day Total Sales ": 0.0, "Total Return on Advertising Spend (RoAS)": 0.0, "7 Day Total Orders (#)": 0, "7 Day Total Units (#)": 0, "7 Day Conversion Rate": 0.0, "7 Day Advertised SKU Units (#)": 0, "7 Day Other SKU Units (#)": 0, "7 Day Advertised SKU Sales ": 0.0, "7 Day Other SKU Sales ": 0 }, "geometry": null },
{ "type": "Feature", "properties": { "Start Date": 43647, "End Date": 43647, "Portfolio name": "Not grouped", "Currency": "USD", "Campaign Name": "OraSwift SKU2 Auto", "Ad Group Name": "OraSwift", "Targeting": "*", "Match Type": "-", "Customer Search Term": "b01avfmwyu", "Impressions": 27, "Clicks": 1, "Click-Thru Rate (CTR)": 0.037037037037037035, "Cost Per Click (CPC)": 1.86, "Spend": 1.86, "7 Day Total Sales ": 0.0, "Total Return on Advertising Spend (RoAS)": 0.0, "7 Day Total Orders (#)": 0, "7 Day Total Units (#)": 0, "7 Day Conversion Rate": 0.0, "7 Day Advertised SKU Units (#)": 0, "7 Day Other SKU Units (#)": 0, "7 Day Advertised SKU Sales ": 0.0, "7 Day Other SKU Sales ": 0 }, "geometry": null },
{ "type": "Feature", "properties": { "Start Date": 43647, "End Date": 43647, "Portfolio name": "Not grouped", "Currency": "USD", "Campaign Name": "OraSwift SKU2 Auto", "Ad Group Name": "OraSwift", "Targeting": "*", "Match Type": "-", "Customer Search Term": "b01b22ogng", "Impressions": 98, "Clicks": 1, "Click-Thru Rate (CTR)": 0.010204081632653062, "Cost Per Click (CPC)": 1.88, "Spend": 1.88, "7 Day Total Sales ": 0.0, "Total Return on Advertising Spend (RoAS)": 0.0, "7 Day Total Orders (#)": 0, "7 Day Total Units (#)": 0, "7 Day Conversion Rate": 0.0, "7 Day Advertised SKU Units (#)": 0, "7 Day Other SKU Units (#)": 0, "7 Day Advertised SKU Sales ": 0.0, "7 Day Other SKU Sales ": 0 }, "geometry": null },
{ "type": "Feature", "properties": { "Start Date": 43649, "End Date": 43675, "Portfolio name": "Not grouped", "Currency": "USD", "Campaign Name": "OraSwift SKU2 Auto", "Ad Group Name": "OraSwift", "Targeting": "*", "Match Type": "-", "Customer Search Term": "b01c6qddj0", "Impressions": 1139, "Clicks": 12, "Click-Thru Rate (CTR)": 0.010535557506584723, "Cost Per Click (CPC)": 1.5383333333333333, "Spend": 18.46, "7 Day Total Sales ": 19.95, "Total Advertising Cost of Sales (ACoS) ": "0.92531328320802009", "Total Return on Advertising Spend (RoAS)": 1.0807150595882988, "7 Day Total Orders (#)": 1, "7 Day Total Units (#)": 1, "7 Day Conversion Rate": 0.083333333333333315, "7 Day Advertised SKU Units (#)": 1, "7 Day Other SKU Units (#)": 0, "7 Day Advertised SKU Sales ": 19.95, "7 Day Other SKU Sales ": 0 }, "geometry": null },
{ "type": "Feature", "properties": { "Start Date": 43667, "End Date": 43667, "Portfolio name": "Not grouped", "Currency": "USD", "Campaign Name": "OraSwift SKU2 Auto", "Ad Group Name": "OraSwift", "Targeting": "*", "Match Type": "-", "Customer Search Term": "b01fxcjria", "Impressions": 9, "Clicks": 1, "Click-Thru Rate (CTR)": 0.1111111111111111, "Cost Per Click (CPC)": 1.26, "Spend": 1.26, "7 Day Total Sales ": 0.0, "Total Return on Advertising Spend (RoAS)": 0.0, "7 Day Total Orders (#)": 0, "7 Day Total Units (#)": 0, "7 Day Conversion Rate": 0.0, "7 Day Advertised SKU Units (#)": 0, "7 Day Other SKU Units (#)": 0, "7 Day Advertised SKU Sales ": 0.0, "7 Day Other SKU Sales ": 0 }, "geometry": null },
{ "type": "Feature", "properties": { "Start Date": 43652, "End Date": 43652, "Portfolio name": "Not grouped", "Currency": "USD", "Campaign Name": "OraSwift SKU2 Auto", "Ad Group Name": "OraSwift", "Targeting": "*", "Match Type": "-", "Customer Search Term": "b01j4lxi0o", "Impressions": 7, "Clicks": 1, "Click-Thru Rate (CTR)": 0.14285714285714285, "Cost Per Click (CPC)": 1.92, "Spend": 1.92, "7 Day Total Sales ": 0.0, "Total Return on Advertising Spend (RoAS)": 0.0, "7 Day Total Orders (#)": 0, "7 Day Total Units (#)": 0, "7 Day Conversion Rate": 0.0, "7 Day Advertised SKU Units (#)": 0, "7 Day Other SKU Units (#)": 0, "7 Day Advertised SKU Sales ": 0.0, "7 Day Other SKU Sales ": 0 }, "geometry": null },
{ "type": "Feature", "properties": { "Start Date": 43657, "End Date": 43657, "Portfolio name": "Not grouped", "Currency": "USD", "Campaign Name": "OraSwift SKU2 Auto", "Ad Group Name": "OraSwift", "Targeting": "*", "Match Type": "-", "Customer Search Term": "b01lzs11mc", "Impressions": 8, "Clicks": 1, "Click-Thru Rate (CTR)": 0.125, "Cost Per Click (CPC)": 0.54, "Spend": 0.54, "7 Day Total Sales ": 0.0, "Total Return on Advertising Spend (RoAS)": 0.0, "7 Day Total Orders (#)": 0, "7 Day Total Units (#)": 0, "7 Day Conversion Rate": 0.0, "7 Day Advertised SKU Units (#)": 0, "7 Day Other SKU Units (#)": 0, "7 Day Advertised SKU Sales ": 0.0, "7 Day Other SKU Sales ": 0 }, "geometry": null },
{ "type": "Feature", "properties": { "Start Date": 43658, "End Date": 43675, "Portfolio name": "Not grouped", "Currency": "USD", "Campaign Name": "OraSwift SKU2 Auto", "Ad Group Name": "OraSwift", "Targeting": "*", "Match Type": "-", "Customer Search Term": "b01m1mssde", "Impressions": 298, "Clicks": 6, "Click-Thru Rate (CTR)": 0.020134228187919462, "Cost Per Click (CPC)": 1.215, "Spend": 7.29, "7 Day Total Sales ": 19.95, "Total Advertising Cost of Sales (ACoS) ": "0.36541353383458658", "Total Return on Advertising Spend (RoAS)": 2.7366255144032916, "7 Day Total Orders (#)": 1, "7 Day Total Units (#)": 1, "7 Day Conversion Rate": 0.16666666666666663, "7 Day Advertised SKU Units (#)": 1, "7 Day Other SKU Units (#)": 0, "7 Day Advertised SKU Sales ": 19.95, "7 Day Other SKU Sales ": 0 }, "geometry": null },
{ "type": "Feature", "properties": { "Start Date": 43650, "End Date": 43650, "Portfolio name": "Not grouped", "Currency": "USD", "Campaign Name": "OraSwift SKU2 Auto", "Ad Group Name": "OraSwift", "Targeting": "*", "Match Type": "-", "Customer Search Term": "b01m3z6wwu", "Impressions": 4, "Clicks": 1, "Click-Thru Rate (CTR)": 0.25, "Cost Per Click (CPC)": 0.3, "Spend": 0.3, "7 Day Total Sales ": 0.0, "Total Return on Advertising Spend (RoAS)": 0.0, "7 Day Total Orders (#)": 0, "7 Day Total Units (#)": 0, "7 Day Conversion Rate": 0.0, "7 Day Advertised SKU Units (#)": 0, "7 Day Other SKU Units (#)": 0, "7 Day Advertised SKU Sales ": 0.0, "7 Day Other SKU Sales ": 0 }, "geometry": null },
{ "type": "Feature", "properties": { "Start Date": 43656, "End Date": 43658, "Portfolio name": "Not grouped", "Currency": "USD", "Campaign Name": "OraSwift SKU2 Auto", "Ad Group Name": "OraSwift", "Targeting": "*", "Match Type": "-", "Customer Search Term": "b01mtdqxm5", "Impressions": 52, "Clicks": 3, "Click-Thru Rate (CTR)": 0.057692307692307689, "Cost Per Click (CPC)": 1.8966666666666667, "Spend": 5.69, "7 Day Total Sales ": 0.0, "Total Return on Advertising Spend (RoAS)": 0.0, "7 Day Total Orders (#)": 0, "7 Day Total Units (#)": 0, "7 Day Conversion Rate": 0.0, "7 Day Advertised SKU Units (#)": 0, "7 Day Other SKU Units (#)": 0, "7 Day Advertised SKU Sales ": 0.0, "7 Day Other SKU Sales ": 0 }, "geometry": null },
{ "type": "Feature", "properties": { "Start Date": 43649, "End Date": 43649, "Portfolio name": "Not grouped", "Currency": "USD", "Campaign Name": "OraSwift SKU2 Auto", "Ad Group Name": "OraSwift", "Targeting": "*", "Match Type": "-", "Customer Search Term": "b01mxhkgsh", "Impressions": 7, "Clicks": 1, "Click-Thru Rate (CTR)": 0.14285714285714285, "Cost Per Click (CPC)": 0.9, "Spend": 0.9, "7 Day Total Sales ": 0.0, "Total Return on Advertising Spend (RoAS)": 0.0, "7 Day Total Orders (#)": 0, "7 Day Total Units (#)": 0, "7 Day Conversion Rate": 0.0, "7 Day Advertised SKU Units (#)": 0, "7 Day Other SKU Units (#)": 0, "7 Day Advertised SKU Sales ": 0.0, "7 Day Other SKU Sales ": 0 }, "geometry": null },
{ "type": "Feature", "properties": { "Start Date": 43658, "End Date": 43658, "Portfolio name": "Not grouped", "Currency": "USD", "Campaign Name": "OraSwift SKU2 Auto", "Ad Group Name": "OraSwift", "Targeting": "*", "Match Type": "-", "Customer Search Term": "b01n5h4uz7", "Impressions": 25, "Clicks": 1, "Click-Thru Rate (CTR)": 0.04, "Cost Per Click (CPC)": 2.0, "Spend": 2.0, "7 Day Total Sales ": 0.0, "Total Return on Advertising Spend (RoAS)": 0.0, "7 Day Total Orders (#)": 0, "7 Day Total Units (#)": 0, "7 Day Conversion Rate": 0.0, "7 Day Advertised SKU Units (#)": 0, "7 Day Other SKU Units (#)": 0, "7 Day Advertised SKU Sales ": 0.0, "7 Day Other SKU Sales ": 0 }, "geometry": null },
{ "type": "Feature", "properties": { "Start Date": 43653, "End Date": 43653, "Portfolio name": "Not grouped", "Currency": "USD", "Campaign Name": "OraSwift SKU2 Auto", "Ad Group Name": "OraSwift", "Targeting": "*", "Match Type": "-", "Customer Search Term": "b01ncu31e5", "Impressions": 51, "Clicks": 1, "Click-Thru Rate (CTR)": 0.019607843137254902, "Cost Per Click (CPC)": 1.48, "Spend": 1.48, "7 Day Total Sales ": 0.0, "Total Return on Advertising Spend (RoAS)": 0.0, "7 Day Total Orders (#)": 0, "7 Day Total Units (#)": 0, "7 Day Conversion Rate": 0.0, "7 Day Advertised SKU Units (#)": 0, "7 Day Other SKU Units (#)": 0, "7 Day Advertised SKU Sales ": 0.0, "7 Day Other SKU Sales ": 0 }, "geometry": null },
{ "type": "Feature", "properties": { "Start Date": 43657, "End Date": 43657, "Portfolio name": "Not grouped", "Currency": "USD", "Campaign Name": "OraSwift SKU2 Auto", "Ad Group Name": "OraSwift", "Targeting": "*", "Match Type": "-", "Customer Search Term": "b06w5rmvh6", "Impressions": 42, "Clicks": 1, "Click-Thru Rate (CTR)": 0.023809523809523808, "Cost Per Click (CPC)": 1.87, "Spend": 1.87, "7 Day Total Sales ": 0.0, "Total Return on Advertising Spend (RoAS)": 0.0, "7 Day Total Orders (#)": 0, "7 Day Total Units (#)": 0, "7 Day Conversion Rate": 0.0, "7 Day Advertised SKU Units (#)": 0, "7 Day Other SKU Units (#)": 0, "7 Day Advertised SKU Sales ": 0.0, "7 Day Other SKU Sales ": 0 }, "geometry": null },
{ "type": "Feature", "properties": { "Start Date": 43653, "End Date": 43653, "Portfolio name": "Not grouped", "Currency": "USD", "Campaign Name": "OraSwift SKU2 Auto", "Ad Group Name": "OraSwift", "Targeting": "*", "Match Type": "-", "Customer Search Term": "b06y6lfxc7", "Impressions": 6, "Clicks": 1, "Click-Thru Rate (CTR)": 0.16666666666666663, "Cost Per Click (CPC)": 1.49, "Spend": 1.49, "7 Day Total Sales ": 0.0, "Total Return on Advertising Spend (RoAS)": 0.0, "7 Day Total Orders (#)": 0, "7 Day Total Units (#)": 0, "7 Day Conversion Rate": 0.0, "7 Day Advertised SKU Units (#)": 0, "7 Day Other SKU Units (#)": 0, "7 Day Advertised SKU Sales ": 0.0, "7 Day Other SKU Sales ": 0 }, "geometry": null },
{ "type": "Feature", "properties": { "Start Date": 43656, "End Date": 43656, "Portfolio name": "Not grouped", "Currency": "USD", "Campaign Name": "OraSwift SKU2 Auto", "Ad Group Name": "OraSwift", "Targeting": "*", "Match Type": "-", "Customer Search Term": "b071k8pfhg", "Impressions": 193, "Clicks": 1, "Click-Thru Rate (CTR)": 0.0051813471502590684, "Cost Per Click (CPC)": 1.94, "Spend": 1.94, "7 Day Total Sales ": 0.0, "Total Return on Advertising Spend (RoAS)": 0.0, "7 Day Total Orders (#)": 0, "7 Day Total Units (#)": 0, "7 Day Conversion Rate": 0.0, "7 Day Advertised SKU Units (#)": 0, "7 Day Other SKU Units (#)": 0, "7 Day Advertised SKU Sales ": 0.0, "7 Day Other SKU Sales ": 0 }, "geometry": null },
{ "type": "Feature", "properties": { "Start Date": 43676, "End Date": 43676, "Portfolio name": "Not grouped", "Currency": "USD", "Campaign Name": "OraSwift SKU2 Auto", "Ad Group Name": "OraSwift", "Targeting": "*", "Match Type": "-", "Customer Search Term": "b073sy7pv8", "Impressions": 13, "Clicks": 1, "Click-Thru Rate (CTR)": 0.076923076923076927, "Cost Per Click (CPC)": 1.68, "Spend": 1.68, "7 Day Total Sales ": 0.0, "Total Return on Advertising Spend (RoAS)": 0.0, "7 Day Total Orders (#)": 0, "7 Day Total Units (#)": 0, "7 Day Conversion Rate": 0.0, "7 Day Advertised SKU Units (#)": 0, "7 Day Other SKU Units (#)": 0, "7 Day Advertised SKU Sales ": 0.0, "7 Day Other SKU Sales ": 0 }, "geometry": null },
{ "type": "Feature", "properties": { "Start Date": 43677, "End Date": 43677, "Portfolio name": "Not grouped", "Currency": "USD", "Campaign Name": "OraSwift SKU2 Auto", "Ad Group Name": "OraSwift", "Targeting": "*", "Match Type": "-", "Customer Search Term": "b073v47bys", "Impressions": 40, "Clicks": 1, "Click-Thru Rate (CTR)": 0.025, "Cost Per Click (CPC)": 1.83, "Spend": 1.83, "7 Day Total Sales ": 0.0, "Total Return on Advertising Spend (RoAS)": 0.0, "7 Day Total Orders (#)": 0, "7 Day Total Units (#)": 0, "7 Day Conversion Rate": 0.0, "7 Day Advertised SKU Units (#)": 0, "7 Day Other SKU Units (#)": 0, "7 Day Advertised SKU Sales ": 0.0, "7 Day Other SKU Sales ": 0 }, "geometry": null },
{ "type": "Feature", "properties": { "Start Date": 43656, "End Date": 43668, "Portfolio name": "Not grouped", "Currency": "USD", "Campaign Name": "OraSwift SKU2 Auto", "Ad Group Name": "OraSwift", "Targeting": "*", "Match Type": "-", "Customer Search Term": "b0744j8b8g", "Impressions": 263, "Clicks": 3, "Click-Thru Rate (CTR)": 0.011406844106463879, "Cost Per Click (CPC)": 1.843333333333333, "Spend": 5.53, "7 Day Total Sales ": 0.0, "Total Return on Advertising Spend (RoAS)": 0.0, "7 Day Total Orders (#)": 0, "7 Day Total Units (#)": 0, "7 Day Conversion Rate": 0.0, "7 Day Advertised SKU Units (#)": 0, "7 Day Other SKU Units (#)": 0, "7 Day Advertised SKU Sales ": 0.0, "7 Day Other SKU Sales ": 0 }, "geometry": null },
{ "type": "Feature", "properties": { "Start Date": 43677, "End Date": 43677, "Portfolio name": "Not grouped", "Currency": "USD", "Campaign Name": "OraSwift SKU2 Auto", "Ad Group Name": "OraSwift", "Targeting": "*", "Match Type": "-", "Customer Search Term": "b0744jc7tq", "Impressions": 39, "Clicks": 1, "Click-Thru Rate (CTR)": 0.02564102564102564, "Cost Per Click (CPC)": 1.36, "Spend": 1.36, "7 Day Total Sales ": 0.0, "Total Return on Advertising Spend (RoAS)": 0.0, "7 Day Total Orders (#)": 0, "7 Day Total Units (#)": 0, "7 Day Conversion Rate": 0.0, "7 Day Advertised SKU Units (#)": 0, "7 Day Other SKU Units (#)": 0, "7 Day Advertised SKU Sales ": 0.0, "7 Day Other SKU Sales ": 0 }, "geometry": null },
{ "type": "Feature", "properties": { "Start Date": 43654, "End Date": 43654, "Portfolio name": "Not grouped", "Currency": "USD", "Campaign Name": "OraSwift SKU2 Auto", "Ad Group Name": "OraSwift", "Targeting": "*", "Match Type": "-", "Customer Search Term": "b077y6cd38", "Impressions": 2, "Clicks": 1, "Click-Thru Rate (CTR)": 0.5, "Cost Per Click (CPC)": 1.47, "Spend": 1.47, "7 Day Total Sales ": 19.95, "Total Advertising Cost of Sales (ACoS) ": "7.3684210526315796E-2", "Total Return on Advertising Spend (RoAS)": 13.571428571428571, "7 Day Total Orders (#)": 1, "7 Day Total Units (#)": 1, "7 Day Conversion Rate": 1.0, "7 Day Advertised SKU Units (#)": 1, "7 Day Other SKU Units (#)": 0, "7 Day Advertised SKU Sales ": 19.95, "7 Day Other SKU Sales ": 0 }, "geometry": null },
{ "type": "Feature", "properties": { "Start Date": 43652, "End Date": 43656, "Portfolio name": "Not grouped", "Currency": "USD", "Campaign Name": "OraSwift SKU2 Auto", "Ad Group Name": "OraSwift", "Targeting": "*", "Match Type": "-", "Customer Search Term": "b078877knv", "Impressions": 111, "Clicks": 3, "Click-Thru Rate (CTR)": 0.027027027027027025, "Cost Per Click (CPC)": 1.6633333333333333, "Spend": 4.99, "7 Day Total Sales ": 0.0, "Total Return on Advertising Spend (RoAS)": 0.0, "7 Day Total Orders (#)": 0, "7 Day Total Units (#)": 0, "7 Day Conversion Rate": 0.0, "7 Day Advertised SKU Units (#)": 0, "7 Day Other SKU Units (#)": 0, "7 Day Advertised SKU Sales ": 0.0, "7 Day Other SKU Sales ": 0 }, "geometry": null },
{ "type": "Feature", "properties": { "Start Date": 43653, "End Date": 43676, "Portfolio name": "Not grouped", "Currency": "USD", "Campaign Name": "OraSwift SKU2 Auto", "Ad Group Name": "OraSwift", "Targeting": "*", "Match Type": "-", "Customer Search Term": "b07887rk95", "Impressions": 616, "Clicks": 4, "Click-Thru Rate (CTR)": 0.0064935064935064931, "Cost Per Click (CPC)": 1.6225, "Spend": 6.49, "7 Day Total Sales ": 0.0, "Total Return on Advertising Spend (RoAS)": 0.0, "7 Day Total Orders (#)": 0, "7 Day Total Units (#)": 0, "7 Day Conversion Rate": 0.0, "7 Day Advertised SKU Units (#)": 0, "7 Day Other SKU Units (#)": 0, "7 Day Advertised SKU Sales ": 0.0, "7 Day Other SKU Sales ": 0 }, "geometry": null },
{ "type": "Feature", "properties": { "Start Date": 43668, "End Date": 43668, "Portfolio name": "Not grouped", "Currency": "USD", "Campaign Name": "OraSwift SKU2 Auto", "Ad Group Name": "OraSwift", "Targeting": "*", "Match Type": "-", "Customer Search Term": "b07889dyhh", "Impressions": 15, "Clicks": 1, "Click-Thru Rate (CTR)": 0.066666666666666666, "Cost Per Click (CPC)": 1.86, "Spend": 1.86, "7 Day Total Sales ": 0.0, "Total Return on Advertising Spend (RoAS)": 0.0, "7 Day Total Orders (#)": 0, "7 Day Total Units (#)": 0, "7 Day Conversion Rate": 0.0, "7 Day Advertised SKU Units (#)": 0, "7 Day Other SKU Units (#)": 0, "7 Day Advertised SKU Sales ": 0.0, "7 Day Other SKU Sales ": 0 }, "geometry": null },
{ "type": "Feature", "properties": { "Start Date": 43672, "End Date": 43672, "Portfolio name": "Not grouped", "Currency": "USD", "Campaign Name": "OraSwift SKU2 Auto", "Ad Group Name": "OraSwift", "Targeting": "*", "Match Type": "-", "Customer Search Term": "b079yb9pz6", "Impressions": 28, "Clicks": 1, "Click-Thru Rate (CTR)": 0.035714285714285712, "Cost Per Click (CPC)": 1.73, "Spend": 1.73, "7 Day Total Sales ": 0.0, "Total Return on Advertising Spend (RoAS)": 0.0, "7 Day Total Orders (#)": 0, "7 Day Total Units (#)": 0, "7 Day Conversion Rate": 0.0, "7 Day Advertised SKU Units (#)": 0, "7 Day Other SKU Units (#)": 0, "7 Day Advertised SKU Sales ": 0.0, "7 Day Other SKU Sales ": 0 }, "geometry": null },
{ "type": "Feature", "properties": { "Start Date": 43656, "End Date": 43656, "Portfolio name": "Not grouped", "Currency": "USD", "Campaign Name": "OraSwift SKU2 Auto", "Ad Group Name": "OraSwift", "Targeting": "*", "Match Type": "-", "Customer Search Term": "b07b5dtvpk", "Impressions": 32, "Clicks": 1, "Click-Thru Rate (CTR)": 0.03125, "Cost Per Click (CPC)": 1.97, "Spend": 1.97, "7 Day Total Sales ": 0.0, "Total Return on Advertising Spend (RoAS)": 0.0, "7 Day Total Orders (#)": 0, "7 Day Total Units (#)": 0, "7 Day Conversion Rate": 0.0, "7 Day Advertised SKU Units (#)": 0, "7 Day Other SKU Units (#)": 0, "7 Day Advertised SKU Sales ": 0.0, "7 Day Other SKU Sales ": 0 }, "geometry": null },
{ "type": "Feature", "properties": { "Start Date": 43654, "End Date": 43654, "Portfolio name": "Not grouped", "Currency": "USD", "Campaign Name": "OraSwift SKU2 Auto", "Ad Group Name": "OraSwift", "Targeting": "*", "Match Type": "-", "Customer Search Term": "b07bwvjng2", "Impressions": 10, "Clicks": 1, "Click-Thru Rate (CTR)": 0.1, "Cost Per Click (CPC)": 1.67, "Spend": 1.67, "7 Day Total Sales ": 19.95, "Total Advertising Cost of Sales (ACoS) ": "8.3709273182957386E-2", "Total Return on Advertising Spend (RoAS)": 11.946107784431138, "7 Day Total Orders (#)": 1, "7 Day Total Units (#)": 1, "7 Day Conversion Rate": 1.0, "7 Day Advertised SKU Units (#)": 1, "7 Day Other SKU Units (#)": 0, "7 Day Advertised SKU Sales ": 19.95, "7 Day Other SKU Sales ": 0 }, "geometry": null },
{ "type": "Feature", "properties": { "Start Date": 43652, "End Date": 43675, "Portfolio name": "Not grouped", "Currency": "USD", "Campaign Name": "OraSwift SKU2 Auto", "Ad Group Name": "OraSwift", "Targeting": "*", "Match Type": "-", "Customer Search Term": "b07c63ssh8", "Impressions": 858, "Clicks": 8, "Click-Thru Rate (CTR)": 0.009324009324009324, "Cost Per Click (CPC)": 1.86125, "Spend": 14.89, "7 Day Total Sales ": 0.0, "Total Return on Advertising Spend (RoAS)": 0.0, "7 Day Total Orders (#)": 0, "7 Day Total Units (#)": 0, "7 Day Conversion Rate": 0.0, "7 Day Advertised SKU Units (#)": 0, "7 Day Other SKU Units (#)": 0, "7 Day Advertised SKU Sales ": 0.0, "7 Day Other SKU Sales ": 0 }, "geometry": null },
{ "type": "Feature", "properties": { "Start Date": 43649, "End Date": 43649, "Portfolio name": "Not grouped", "Currency": "USD", "Campaign Name": "OraSwift SKU2 Auto", "Ad Group Name": "OraSwift", "Targeting": "*", "Match Type": "-", "Customer Search Term": "b07f2sp74b", "Impressions": 25, "Clicks": 1, "Click-Thru Rate (CTR)": 0.04, "Cost Per Click (CPC)": 1.84, "Spend": 1.84, "7 Day Total Sales ": 0.0, "Total Return on Advertising Spend (RoAS)": 0.0, "7 Day Total Orders (#)": 0, "7 Day Total Units (#)": 0, "7 Day Conversion Rate": 0.0, "7 Day Advertised SKU Units (#)": 0, "7 Day Other SKU Units (#)": 0, "7 Day Advertised SKU Sales ": 0.0, "7 Day Other SKU Sales ": 0 }, "geometry": null },
{ "type": "Feature", "properties": { "Start Date": 43659, "End Date": 43659, "Portfolio name": "Not grouped", "Currency": "USD", "Campaign Name": "OraSwift SKU2 Auto", "Ad Group Name": "OraSwift", "Targeting": "*", "Match Type": "-", "Customer Search Term": "b07mvmpqlh", "Impressions": 117, "Clicks": 1, "Click-Thru Rate (CTR)": 0.0085470085470085479, "Cost Per Click (CPC)": 1.96, "Spend": 1.96, "7 Day Total Sales ": 0.0, "Total Return on Advertising Spend (RoAS)": 0.0, "7 Day Total Orders (#)": 0, "7 Day Total Units (#)": 0, "7 Day Conversion Rate": 0.0, "7 Day Advertised SKU Units (#)": 0, "7 Day Other SKU Units (#)": 0, "7 Day Advertised SKU Sales ": 0.0, "7 Day Other SKU Sales ": 0 }, "geometry": null },
{ "type": "Feature", "properties": { "Start Date": 43672, "End Date": 43672, "Portfolio name": "Not grouped", "Currency": "USD", "Campaign Name": "OraSwift SKU2 Auto", "Ad Group Name": "OraSwift", "Targeting": "*", "Match Type": "-", "Customer Search Term": "b07qtx8xlw", "Impressions": 17, "Clicks": 1, "Click-Thru Rate (CTR)": 0.058823529411764698, "Cost Per Click (CPC)": 1.87, "Spend": 1.87, "7 Day Total Sales ": 0.0, "Total Return on Advertising Spend (RoAS)": 0.0, "7 Day Total Orders (#)": 0, "7 Day Total Units (#)": 0, "7 Day Conversion Rate": 0.0, "7 Day Advertised SKU Units (#)": 0, "7 Day Other SKU Units (#)": 0, "7 Day Advertised SKU Sales ": 0.0, "7 Day Other SKU Sales ": 0 }, "geometry": null },
{ "type": "Feature", "properties": { "Start Date": 43659, "End Date": 43669, "Portfolio name": "Not grouped", "Currency": "USD", "Campaign Name": "OraSwift SKU2 Auto", "Ad Group Name": "OraSwift", "Targeting": "*", "Match Type": "-", "Customer Search Term": "b07r3cf4y9", "Impressions": 256, "Clicks": 3, "Click-Thru Rate (CTR)": 0.01171875, "Cost Per Click (CPC)": 1.843333333333333, "Spend": 5.53, "7 Day Total Sales ": 0.0, "Total Return on Advertising Spend (RoAS)": 0.0, "7 Day Total Orders (#)": 0, "7 Day Total Units (#)": 0, "7 Day Conversion Rate": 0.0, "7 Day Advertised SKU Units (#)": 0, "7 Day Other SKU Units (#)": 0, "7 Day Advertised SKU Sales ": 0.0, "7 Day Other SKU Sales ": 0 }, "geometry": null },
{ "type": "Feature", "properties": { "Start Date": 43664, "End Date": 43664, "Portfolio name": "Not grouped", "Currency": "USD", "Campaign Name": "OraSwift SKU2 Auto", "Ad Group Name": "OraSwift", "Targeting": "*", "Match Type": "-", "Customer Search Term": "b07rg5tvg5", "Impressions": 25, "Clicks": 1, "Click-Thru Rate (CTR)": 0.04, "Cost Per Click (CPC)": 1.56, "Spend": 1.56, "7 Day Total Sales ": 0.0, "Total Return on Advertising Spend (RoAS)": 0.0, "7 Day Total Orders (#)": 0, "7 Day Total Units (#)": 0, "7 Day Conversion Rate": 0.0, "7 Day Advertised SKU Units (#)": 0, "7 Day Other SKU Units (#)": 0, "7 Day Advertised SKU Sales ": 0.0, "7 Day Other SKU Sales ": 0 }, "geometry": null },
{ "type": "Feature", "properties": { "Start Date": 43667, "End Date": 43667, "Portfolio name": "Not grouped", "Currency": "USD", "Campaign Name": "OraSwift SKU2 Auto", "Ad Group Name": "OraSwift", "Targeting": "*", "Match Type": "-", "Customer Search Term": "canker mouth sores", "Impressions": 3, "Clicks": 1, "Click-Thru Rate (CTR)": 0.33333333333333326, "Cost Per Click (CPC)": 1.39, "Spend": 1.39, "7 Day Total Sales ": 0.0, "Total Return on Advertising Spend (RoAS)": 0.0, "7 Day Total Orders (#)": 0, "7 Day Total Units (#)": 0, "7 Day Conversion Rate": 0.0, "7 Day Advertised SKU Units (#)": 0, "7 Day Other SKU Units (#)": 0, "7 Day Advertised SKU Sales ": 0.0, "7 Day Other SKU Sales ": 0 }, "geometry": null },
{ "type": "Feature", "properties": { "Start Date": 43665, "End Date": 43665, "Portfolio name": "Not grouped", "Currency": "USD", "Campaign Name": "OraSwift SKU2 Auto", "Ad Group Name": "OraSwift", "Targeting": "*", "Match Type": "-", "Customer Search Term": "canker relief", "Impressions": 2, "Clicks": 1, "Click-Thru Rate (CTR)": 0.5, "Cost Per Click (CPC)": 0.99, "Spend": 0.99, "7 Day Total Sales ": 0.0, "Total Return on Advertising Spend (RoAS)": 0.0, "7 Day Total Orders (#)": 0, "7 Day Total Units (#)": 0, "7 Day Conversion Rate": 0.0, "7 Day Advertised SKU Units (#)": 0, "7 Day Other SKU Units (#)": 0, "7 Day Advertised SKU Sales ": 0.0, "7 Day Other SKU Sales ": 0 }, "geometry": null },
{ "type": "Feature", "properties": { "Start Date": 43659, "End Date": 43659, "Portfolio name": "Not grouped", "Currency": "USD", "Campaign Name": "OraSwift SKU2 Auto", "Ad Group Name": "OraSwift", "Targeting": "*", "Match Type": "-", "Customer Search Term": "canker sore lozenge", "Impressions": 1, "Clicks": 1, "Click-Thru Rate (CTR)": 1.0, "Cost Per Click (CPC)": 0.98, "Spend": 0.98, "7 Day Total Sales ": 0.0, "Total Return on Advertising Spend (RoAS)": 0.0, "7 Day Total Orders (#)": 0, "7 Day Total Units (#)": 0, "7 Day Conversion Rate": 0.0, "7 Day Advertised SKU Units (#)": 0, "7 Day Other SKU Units (#)": 0, "7 Day Advertised SKU Sales ": 0.0, "7 Day Other SKU Sales ": 0 }, "geometry": null },
{ "type": "Feature", "properties": { "Start Date": 43659, "End Date": 43659, "Portfolio name": "Not grouped", "Currency": "USD", "Campaign Name": "OraSwift SKU2 Auto", "Ad Group Name": "OraSwift", "Targeting": "*", "Match Type": "-", "Customer Search Term": "canker sore relief", "Impressions": 5, "Clicks": 1, "Click-Thru Rate (CTR)": 0.2, "Cost Per Click (CPC)": 1.42, "Spend": 1.42, "7 Day Total Sales ": 19.95, "Total Advertising Cost of Sales (ACoS) ": "7.1177944862155382E-2", "Total Return on Advertising Spend (RoAS)": 14.049295774647888, "7 Day Total Orders (#)": 1, "7 Day Total Units (#)": 1, "7 Day Conversion Rate": 1.0, "7 Day Advertised SKU Units (#)": 1, "7 Day Other SKU Units (#)": 0, "7 Day Advertised SKU Sales ": 19.95, "7 Day Other SKU Sales ": 0 }, "geometry": null },
{ "type": "Feature", "properties": { "Start Date": 43648, "End Date": 43674, "Portfolio name": "Not grouped", "Currency": "USD", "Campaign Name": "OraSwift SKU2 Auto", "Ad Group Name": "OraSwift", "Targeting": "*", "Match Type": "-", "Customer Search Term": "canker sore treatment", "Impressions": 2274, "Clicks": 13, "Click-Thru Rate (CTR)": 0.0057167985927880386, "Cost Per Click (CPC)": 1.7346153846153847, "Spend": 22.55, "7 Day Total Sales ": 0.0, "Total Return on Advertising Spend (RoAS)": 0.0, "7 Day Total Orders (#)": 0, "7 Day Total Units (#)": 0, "7 Day Conversion Rate": 0.0, "7 Day Advertised SKU Units (#)": 0, "7 Day Other SKU Units (#)": 0, "7 Day Advertised SKU Sales ": 0.0, "7 Day Other SKU Sales ": 0 }, "geometry": null },
{ "type": "Feature", "properties": { "Start Date": 43653, "End Date": 43653, "Portfolio name": "Not grouped", "Currency": "USD", "Campaign Name": "OraSwift SKU2 Auto", "Ad Group Name": "OraSwift", "Targeting": "*", "Match Type": "-", "Customer Search Term": "mint for mouth ulcer", "Impressions": 2, "Clicks": 2, "Click-Thru Rate (CTR)": 1.0, "Cost Per Click (CPC)": 0.63, "Spend": 1.26, "7 Day Total Sales ": 0.0, "Total Return on Advertising Spend (RoAS)": 0.0, "7 Day Total Orders (#)": 0, "7 Day Total Units (#)": 0, "7 Day Conversion Rate": 0.0, "7 Day Advertised SKU Units (#)": 0, "7 Day Other SKU Units (#)": 0, "7 Day Advertised SKU Sales ": 0.0, "7 Day Other SKU Sales ": 0 }, "geometry": null },
{ "type": "Feature", "properties": { "Start Date": 43657, "End Date": 43657, "Portfolio name": "Not grouped", "Currency": "USD", "Campaign Name": "OraSwift SKU2 Auto", "Ad Group Name": "OraSwift", "Targeting": "*", "Match Type": "-", "Customer Search Term": "mouth canker sore treatment", "Impressions": 11, "Clicks": 1, "Click-Thru Rate (CTR)": 0.090909090909090912, "Cost Per Click (CPC)": 1.86, "Spend": 1.86, "7 Day Total Sales ": 19.95, "Total Advertising Cost of Sales (ACoS) ": "9.3233082706766932E-2", "Total Return on Advertising Spend (RoAS)": 10.725806451612902, "7 Day Total Orders (#)": 1, "7 Day Total Units (#)": 1, "7 Day Conversion Rate": 1.0, "7 Day Advertised SKU Units (#)": 1, "7 Day Other SKU Units (#)": 0, "7 Day Advertised SKU Sales ": 19.95, "7 Day Other SKU Sales ": 0 }, "geometry": null },
{ "type": "Feature", "properties": { "Start Date": 43655, "End Date": 43673, "Portfolio name": "Not grouped", "Currency": "USD", "Campaign Name": "OraSwift SKU2 Auto", "Ad Group Name": "OraSwift", "Targeting": "*", "Match Type": "-", "Customer Search Term": "mouth sore", "Impressions": 111, "Clicks": 5, "Click-Thru Rate (CTR)": 0.04504504504504505, "Cost Per Click (CPC)": 1.722, "Spend": 8.61, "7 Day Total Sales ": 0.0, "Total Return on Advertising Spend (RoAS)": 0.0, "7 Day Total Orders (#)": 0, "7 Day Total Units (#)": 0, "7 Day Conversion Rate": 0.0, "7 Day Advertised SKU Units (#)": 0, "7 Day Other SKU Units (#)": 0, "7 Day Advertised SKU Sales ": 0.0, "7 Day Other SKU Sales ": 0 }, "geometry": null },
{ "type": "Feature", "properties": { "Start Date": 43659, "End Date": 43666, "Portfolio name": "Not grouped", "Currency": "USD", "Campaign Name": "OraSwift SKU2 Auto", "Ad Group Name": "OraSwift", "Targeting": "*", "Match Type": "-", "Customer Search Term": "mouth sore lozenges", "Impressions": 6, "Clicks": 2, "Click-Thru Rate (CTR)": 0.33333333333333326, "Cost Per Click (CPC)": 1.625, "Spend": 3.25, "7 Day Total Sales ": 0.0, "Total Return on Advertising Spend (RoAS)": 0.0, "7 Day Total Orders (#)": 0, "7 Day Total Units (#)": 0, "7 Day Conversion Rate": 0.0, "7 Day Advertised SKU Units (#)": 0, "7 Day Other SKU Units (#)": 0, "7 Day Advertised SKU Sales ": 0.0, "7 Day Other SKU Sales ": 0 }, "geometry": null },
{ "type": "Feature", "properties": { "Start Date": 43654, "End Date": 43654, "Portfolio name": "Not grouped", "Currency": "USD", "Campaign Name": "OraSwift SKU2 Auto", "Ad Group Name": "OraSwift", "Targeting": "*", "Match Type": "-", "Customer Search Term": "mouth sores", "Impressions": 17, "Clicks": 1, "Click-Thru Rate (CTR)": 0.058823529411764698, "Cost Per Click (CPC)": 1.77, "Spend": 1.77, "7 Day Total Sales ": 0.0, "Total Return on Advertising Spend (RoAS)": 0.0, "7 Day Total Orders (#)": 0, "7 Day Total Units (#)": 0, "7 Day Conversion Rate": 0.0, "7 Day Advertised SKU Units (#)": 0, "7 Day Other SKU Units (#)": 0, "7 Day Advertised SKU Sales ": 0.0, "7 Day Other SKU Sales ": 0 }, "geometry": null },
{ "type": "Feature", "properties": { "Start Date": 43647, "End Date": 43675, "Portfolio name": "Not grouped", "Currency": "USD", "Campaign Name": "OraSwift SKU2 Auto", "Ad Group Name": "OraSwift", "Targeting": "*", "Match Type": "-", "Customer Search Term": "mouth ulcer", "Impressions": 111, "Clicks": 9, "Click-Thru Rate (CTR)": 0.081081081081081086, "Cost Per Click (CPC)": 1.2077777777777778, "Spend": 10.87, "7 Day Total Sales ": 0.0, "Total Return on Advertising Spend (RoAS)": 0.0, "7 Day Total Orders (#)": 0, "7 Day Total Units (#)": 0, "7 Day Conversion Rate": 0.0, "7 Day Advertised SKU Units (#)": 0, "7 Day Other SKU Units (#)": 0, "7 Day Advertised SKU Sales ": 0.0, "7 Day Other SKU Sales ": 0 }, "geometry": null },
{ "type": "Feature", "properties": { "Start Date": 43667, "End Date": 43667, "Portfolio name": "Not grouped", "Currency": "USD", "Campaign Name": "OraSwift SKU2 Auto", "Ad Group Name": "OraSwift", "Targeting": "*", "Match Type": "-", "Customer Search Term": "natural dry mouth treatment", "Impressions": 2, "Clicks": 1, "Click-Thru Rate (CTR)": 0.5, "Cost Per Click (CPC)": 1.06, "Spend": 1.06, "7 Day Total Sales ": 19.95, "Total Advertising Cost of Sales (ACoS) ": "5.3132832080200504E-2", "Total Return on Advertising Spend (RoAS)": 18.820754716981131, "7 Day Total Orders (#)": 1, "7 Day Total Units (#)": 1, "7 Day Conversion Rate": 1.0, "7 Day Advertised SKU Units (#)": 1, "7 Day Other SKU Units (#)": 0, "7 Day Advertised SKU Sales ": 19.95, "7 Day Other SKU Sales ": 0 }, "geometry": null },
{ "type": "Feature", "properties": { "Start Date": 43647, "End Date": 43671, "Portfolio name": "Not grouped", "Currency": "USD", "Campaign Name": "OraSwift SKU2 Auto", "Ad Group Name": "OraSwift", "Targeting": "*", "Match Type": "-", "Customer Search Term": "sore mouth treatment", "Impressions": 239, "Clicks": 3, "Click-Thru Rate (CTR)": 0.012552301255230125, "Cost Per Click (CPC)": 1.6966666666666665, "Spend": 5.09, "7 Day Total Sales ": 0.0, "Total Return on Advertising Spend (RoAS)": 0.0, "7 Day Total Orders (#)": 0, "7 Day Total Units (#)": 0, "7 Day Conversion Rate": 0.0, "7 Day Advertised SKU Units (#)": 0, "7 Day Other SKU Units (#)": 0, "7 Day Advertised SKU Sales ": 0.0, "7 Day Other SKU Sales ": 0 }, "geometry": null },
{ "type": "Feature", "properties": { "Start Date": 43670, "End Date": 43670, "Portfolio name": "Not grouped", "Currency": "USD", "Campaign Name": "OraSwift SKU2 Auto", "Ad Group Name": "OraSwift", "Targeting": "*", "Match Type": "-", "Customer Search Term": "ulcer lozenge", "Impressions": 2, "Clicks": 1, "Click-Thru Rate (CTR)": 0.5, "Cost Per Click (CPC)": 0.32, "Spend": 0.32, "7 Day Total Sales ": 19.95, "Total Advertising Cost of Sales (ACoS) ": "1.6040100250626566E-2", "Total Return on Advertising Spend (RoAS)": 62.34375, "7 Day Total Orders (#)": 1, "7 Day Total Units (#)": 1, "7 Day Conversion Rate": 1.0, "7 Day Advertised SKU Units (#)": 1, "7 Day Other SKU Units (#)": 0, "7 Day Advertised SKU Sales ": 19.95, "7 Day Other SKU Sales ": 0 }, "geometry": null },
{ "type": "Feature", "properties": { "Start Date": 43673, "End Date": 43673, "Portfolio name": "Not grouped", "Currency": "USD", "Campaign Name": "OraSwift SKU2 Auto", "Ad Group Name": "OraSwift", "Targeting": "*", "Match Type": "-", "Customer Search Term": "ulcer treatment", "Impressions": 4, "Clicks": 1, "Click-Thru Rate (CTR)": 0.25, "Cost Per Click (CPC)": 1.63, "Spend": 1.63, "7 Day Total Sales ": 0.0, "Total Return on Advertising Spend (RoAS)": 0.0, "7 Day Total Orders (#)": 0, "7 Day Total Units (#)": 0, "7 Day Conversion Rate": 0.0, "7 Day Advertised SKU Units (#)": 0, "7 Day Other SKU Units (#)": 0, "7 Day Advertised SKU Sales ": 0.0, "7 Day Other SKU Sales ": 0 }, "geometry": null }
]
}
